redshift_auto_schema/RedshiftAutoSchema.py
redshift_auto_schema/__init__.py
redshift_auto_schema-0.1.16.dist-info/LICENSE
redshift_auto_schema-0.1.16.dist-info/METADATA
redshift_auto_schema-0.1.16.dist-info/WHEEL
redshift_auto_schema-0.1.16.dist-info/top_level.txt
redshift_auto_schema-0.1.16.dist-info/RECORD
