Metadata-Version: 2.1
Name: redshift-auto-schema
Version: 0.1.16
Summary: Auto-generate Redshift schemas
Home-page: https://github.com/mikethoun/redshift-auto-schema
Author: Mike Thoun
Author-email: mikethoun@gmail.com
License: Apache License 2.0
Platform: UNKNOWN
Classifier: Programming Language :: Python :: 3
Classifier: License :: OSI Approved :: Apache Software License
Requires-Dist: pandas (>=1.0.0)
Requires-Dist: numpy
